Metadata-Version: 2.1
Name: msb-client-websocket-python
Version: 1.0.16
Summary: The Python client library to connect to the Websocket Interface of the VFK MSB
Home-page: https://research.virtualfortknox.de/
Author: Daniel Stock
Author-email: daniel.stock@ipa.fraunhofer.de
License: Apache-2.0
Project-URL: Source Code, https://github.com/research-virtualfortknox/msb-client-websocket-python.git
Project-URL: Bug Tracker, https://github.com/research-virtualfortknox/msb-client-websocket-python/issues
License-File: LICENSE
Requires-Dist: websocket-client (>=1.6.4)
Requires-Dist: jsonschema (>=4.19.1)
Requires-Dist: enum34 (>=1.1.10)
